lmdbm/__init__.py
lmdbm/lmdbm.py
lmdbm/py.typed
lmdbm-0.0.6.dist-info/WHEEL
lmdbm-0.0.6.dist-info/METADATA
lmdbm-0.0.6.dist-info/RECORD
