Metadata-Version: 2.1
Name: lmdbm
Version: 0.0.6
Summary: Python DBM style wrapper around LMDB (Lightning Memory-Mapped Database)
Author-email: Dobatymo <Dobatymo@users.noreply.github.com>
Requires-Python: >= 3.7
Classifier: Intended Audience :: Developers
Classifier: License :: OSI Approved :: ISC License (ISCL)
Classifier: Operating System :: OS Independent
Classifier: Programming Language :: Python :: 3 :: Only
Classifier: Programming Language :: Python :: 3.7
Classifier: Programming Language :: Python :: 3.8
Classifier: Programming Language :: Python :: 3.9
Classifier: Programming Language :: Python :: 3.10
Classifier: Programming Language :: Python :: 3.11
Classifier: Programming Language :: Python :: 3.12
Classifier: Topic :: Database
Requires-Dist: lmdb
Requires-Dist: typing-extensions>=4
Requires-Dist: genutility[iter,rich,time]>=0.0.103 ; extra == "bench"
Requires-Dist: pysos==1.2.9 ; extra == "bench"
Requires-Dist: pytablewriter==0.63 ; extra == "bench"
Requires-Dist: rocksdict==0.3.5 ; extra == "bench"
Requires-Dist: semidbm==0.5.1 ; extra == "bench"
Requires-Dist: sqlitedict==1.7 ; extra == "bench"
Requires-Dist: unqlite==0.9.2 ; extra == "bench"
Requires-Dist: vedis==0.7.1 ; extra == "bench"
Requires-Dist: genutility[test] ; extra == "test"
Project-URL: Home, https://github.com/Dobatymo/lmdb-python-dbm
Provides-Extra: bench
Provides-Extra: test
